digitex_engine_client/__init__.py
digitex_engine_client/auto_async.py
digitex_engine_client/client.py
digitex_engine_client/listener.py
digitex_engine_client/message_proxy.py
digitex_engine_client/messages_pb2.py
digitex_engine_client/mq_client.py
digitex_engine_client/tcp_client.py
digitex_engine_client/ws_client.py
digitex_engine_client-4.145.0.dist-info/LICENSE.txt
digitex_engine_client-4.145.0.dist-info/METADATA
digitex_engine_client-4.145.0.dist-info/WHEEL
digitex_engine_client-4.145.0.dist-info/top_level.txt
digitex_engine_client-4.145.0.dist-info/RECORD
